hacs_anthropic/__init__.py
hacs_anthropic-0.3.1.dist-info/METADATA
hacs_anthropic-0.3.1.dist-info/WHEEL
hacs_anthropic-0.3.1.dist-info/RECORD
